ftfy/__init__.py
ftfy/bad_codecs/__init__.py
ftfy/bad_codecs/sloppy.py
ftfy/bad_codecs/utf8_variants.py
ftfy/badness.py
ftfy/chardata.py
ftfy/cli.py
ftfy/fixes.py
ftfy/formatting.py
ftfy/py.typed
ftfy-6.2.2.dist-info/LICENSE.txt
ftfy-6.2.2.dist-info/METADATA
ftfy-6.2.2.dist-info/WHEEL
ftfy-6.2.2.dist-info/entry_points.txt
ftfy-6.2.2.dist-info/RECORD
