Metadata-Version: 2.1
Name: ftfy
Version: 6.2.2
Summary: Fixes mojibake and other problems with Unicode, after the fact
License: Apache-2.0
Author: Robyn Speer
Author-email: rspeer@arborelia.net
Requires-Python: >=3.8.1,<4
Classifier: License :: OSI Approved :: Apache Software License
Classifier: Programming Language :: Python :: 3
Classifier: Programming Language :: Python :: 3.9
Classifier: Programming Language :: Python :: 3.10
Classifier: Programming Language :: Python :: 3.11
Classifier: Programming Language :: Python :: 3.12
Requires-Dist: wcwidth (>=0.2.12,<0.3.0)
